pybrowse/__init__.py
pybrowse-0.1.1.dist-info/AUTHORS
pybrowse-0.1.1.dist-info/LICENSE
pybrowse-0.1.1.dist-info/METADATA
pybrowse-0.1.1.dist-info/WHEEL
pybrowse-0.1.1.dist-info/entry_points.txt
pybrowse-0.1.1.dist-info/pbr.json
pybrowse-0.1.1.dist-info/top_level.txt
pybrowse-0.1.1.dist-info/RECORD
